plone.reload-4.0.0-py3.12-nspkg.pth
plone/reload/__init__.py
plone/reload/browser.py
plone/reload/code.py
plone/reload/config.py
plone/reload/configure.zcml
plone/reload/interfaces.py
plone/reload/reload.pt
plone/reload/template.py
plone/reload/xreload.py
plone/reload/zcml.py
plone/reload/tests/__init__.py
plone/reload/tests/test_code.py
plone/reload/tests/test_reload.py
plone/reload/tests/data/README.txt
plone.reload-4.0.0.dist-info/METADATA
plone.reload-4.0.0.dist-info/WHEEL
plone.reload-4.0.0.dist-info/entry_points.txt
plone.reload-4.0.0.dist-info/namespace_packages.txt
plone.reload-4.0.0.dist-info/top_level.txt
plone.reload-4.0.0.dist-info/RECORD
