Metadata-Version: 2.1
Name: plone.reload
Version: 4.0.0
Summary: Configuration and code reload without server restarts.
Home-page: https://pypi.org/project/plone.reload
Author: Hanno Schlichting
Author-email: hanno@hannosch.eu
License: BSD
Keywords: zope plone reload
Classifier: Development Status :: 5 - Production/Stable
Classifier: Environment :: Web Environment
Classifier: Framework :: Plone
Classifier: Framework :: Zope :: 5
Classifier: License :: OSI Approved :: BSD License
Classifier: Operating System :: OS Independent
Classifier: Programming Language :: Python
Classifier: Programming Language :: Python :: 3
Classifier: Programming Language :: Python :: 3.8
Classifier: Programming Language :: Python :: 3.9
Classifier: Programming Language :: Python :: 3.10
Classifier: Programming Language :: Python :: 3.11
Classifier: Programming Language :: Python :: 3.12
Classifier: Programming Language :: Python :: Implementation :: CPython
Requires-Python: >=3.8
Requires-Dist: setuptools
Requires-Dist: zope.component
Requires-Dist: zope.interface
Requires-Dist: zope.processlifetime
Requires-Dist: zope.publisher
Requires-Dist: zope.site
Requires-Dist: zope.testing
Requires-Dist: Zope
Provides-Extra: cmf
Requires-Dist: Products.CMFCore ; extra == 'cmf'
